<?xml version="1.0" encoding="utf-8"?>
<doctrine-mapping xmlns="http://doctrine-project.org/schemas/orm/doctrine-mapping" xmlns:xsi="http://www.w3.org/2001/XMLSchema-instance" xsi:schemaLocation="http://doctrine-project.org/schemas/orm/doctrine-mapping http://doctrine-project.org/schemas/orm/doctrine-mapping.xsd">
  <entity name="AppBundle\Entity\TClassificacaoirar" table="t_classificacaoirar">
    <unique-constraints>
      <unique-constraint name="IX_t_classificacaoirar_codigo" columns="ft_codigoirar"/>
    </unique-constraints>
    <id name="fnId" type="bigint" column="fn_id">
      <generator strategy="IDENTITY"/>
    </id>
    <field name="ftCodigoirar" type="string" column="ft_codigoirar" length="10" nullable="false"/>
    <field name="fnIdDescricaoirar" type="bigint" column="fn_id_descricaoirar" nullable="false"/>
    <field name="fnIdEntidadegestora" type="bigint" column="fn_id_entidadegestora" nullable="false"/>
    <field name="ftObservacao" type="string" column="ft_observacao" length="300" nullable="true"/>
    <field name="fnIdLocalcolheita" type="bigint" column="fn_id_localcolheita" nullable="false"/>
  </entity>
</doctrine-mapping>
